{
	"configurations" : 
	[
		{
			"directories" : 
			[
				{
					"build" : ".",
					"jsonFile" : "directory-.-Debug-d0094a50bb2071803777.json",
					"minimumCMakeVersion" : 
					{
						"string" : "3.25"
					},
					"projectIndex" : 0,
					"source" : ".",
					"targetIndexes" : 
					[
						0
					]
				}
			],
			"name" : "Debug",
			"projects" : 
			[
				{
					"directoryIndexes" : 
					[
						0
					],
					"name" : "team105",
					"targetIndexes" : 
					[
						0
					]
				}
			],
			"targets" : 
			[
				{
					"directoryIndex" : 0,
					"id" : "team105::@6890427a1f51a3e7e1df",
					"jsonFile" : "target-team105-Debug-4d501357994546403643.json",
					"name" : "team105",
					"projectIndex" : 0
				}
			]
		}
	],
	"kind" : "codemodel",
	"paths" : 
	{
		"build" : "C:/Users/falkb/CLionProjects/team105/cmake-build-debug",
		"source" : "C:/Users/falkb/CLionProjects/team105"
	},
	"version" : 
	{
		"major" : 2,
		"minor" : 4
	}
}
